{
	"Delta Belt": {
		"1": {
			"Biome": "Frozen",
			"Name": "Meuku",
			"Objectites": {
				"Primary": "n/a",
				"Secondary": "n/a"
			},
			"Temperature": -45
		},
		"2": {
			"Biome": "Frozen",
			"Name": "Zioniotke",
			"Objectites": {
				"Primary": "n/a",
				"Secondary": "n/a"
			},
			"Temperature": -53
		},
		"3": {
			"Biome": "Frozen",
			"Name": "Kew",
			"Objectites": {
				"Primary": "n/a",
				"Secondary": "n/a"
			},
			"Temperature": -56
		},
		"4": {
			"Biome": "Stony",
			"Name": "Futonunoulo",
			"Objectites": {
				"Primary": "n/a",
				"Secondary": "n/a"
			},
			"Temperature": 25
		},
		"5": {
			"Biome": "Frozen",
			"Name": "Weuzu",
			"Objectites": {
				"Primary": "n/a",
				"Secondary": "n/a"
			},
			"Temperature": -60
		},
		"6": {
			"Biome": "Frozen",
			"Name": "Suiquukwe",
			"Objectites": {
				"Primary": "n/a",
				"Secondary": "n/a"
			},
			"Temperature": -46
		}
	},
	"Gamma Field": {
		"1": {
			"Biome": "Frozen",
			"Name": "Zyarie",
			"Objectites": {
				"Primary": "n/a",
				"Secondary": "n/a"
			},
			"Temperature": -52
		},
		"2": {
			"Biome": "Vulcanic",
			"Name": "Pejecacuere",
			"Objectites": {
				"Primary": "n/a",
				"Secondary": "n/a"
			},
			"Temperature": 83
		},
		"3": {
			"Biome": "Vulcanic",
			"Name": "Ceidu",
			"Objectites": {
				"Primary": "n/a",
				"Secondary": "n/a"
			},
			"Temperature": 90
		}
	},
	"Lambda Field": {
		"1": {
			"Biome": "Vulcanic",
			"Name": "Piaceogde",
			"Objectites": {
				"Primary": "n/a",
				"Secondary": "n/a"
			},
			"Temperature": 85
		},
		"2": {
			"Biome": "Frozen",
			"Name": "Aqzaa",
			"Objectites": {
				"Primary": "n/a",
				"Secondary": "n/a"
			},
			"Temperature": -47
		},
		"3": {
			"Biome": "Frozen",
			"Name": "Inca-Tifu",
			"Objectites": {
				"Primary": "n/a",
				"Secondary": "n/a"
			},
			"Temperature": -57
		},
		"4": {
			"Biome": "Vulcanic",
			"Name": "Uqvi-Duje",
			"Objectites": {
				"Primary": "n/a",
				"Secondary": "n/a"
			},
			"Temperature": 79
		},
		"5": {
			"Biome": "Frozen",
			"Name": "Paabiebte",
			"Objectites": {
				"Primary": "n/a",
				"Secondary": "n/a"
			},
			"Temperature": -50
		},
		"6": {
			"Biome": "Frozen",
			"Name": "Lab",
			"Objectites": {
				"Primary": "n/a",
				"Secondary": "n/a"
			},
			"Temperature": -57
		},
		"7": {
			"Biome": "Frozen",
			"Name": "Erlu-Gawa",
			"Objectites": {
				"Primary": "n/a",
				"Secondary": "n/a"
			},
			"Temperature": -51
		}
	},
	"Omega Field": {
		"1": {
			"Biome": "Stony",
			"Name": "Ixza-Labi",
			"Objectites": {
				"Primary": "n/a",
				"Secondary": "n/a"
			},
			"Temperature": 22
		},
		"2": {
			"Biome": "Stony",
			"Name": "Sihyic",
			"Objectites": {
				"Primary": "n/a",
				"Secondary": "n/a"
			},
			"Temperature": 26
		},
		"3": {
			"Biome": "Stony",
			"Name": "Piesoufla",
			"Objectites": {
				"Primary": "n/a",
				"Secondary": "n/a"
			},
			"Temperature": 19
		},
		"4": {
			"Biome": "Vulcanic",
			"Name": "Fmosua",
			"Objectites": {
				"Primary": "n/a",
				"Secondary": "n/a"
			},
			"Temperature": 89
		},
		"5": {
			"Biome": "Vulcanic",
			"Name": "Esfee",
			"Objectites": {
				"Primary": "n/a",
				"Secondary": "n/a"
			},
			"Temperature": 83
		},
		"6": {
			"Biome": "Frozen",
			"Name": "Fusoyoyaeyu",
			"Objectites": {
				"Primary": "n/a",
				"Secondary": "n/a"
			},
			"Temperature": -54
		},
		"7": {
			"Biome": "Stony",
			"Name": "Zik",
			"Objectites": {
				"Primary": "n/a",
				"Secondary": "n/a"
			},
			"Temperature": 19
		}
	},
	"Sigma Field": {
		"1": {
			"Biome": "Vulcanic",
			"Name": "Tayororuoco",
			"Objectites": {
				"Primary": "n/a",
				"Secondary": "n/a"
			},
			"Temperature": 85
		},
		"2": {
			"Biome": "Stony",
			"Name": "Zpukei",
			"Objectites": {
				"Primary": "n/a",
				"Secondary": "n/a"
			},
			"Temperature": 22
		},
		"3": {
			"Biome": "Stony",
			"Name": "Huhvut",
			"Objectites": {
				"Primary": "n/a",
				"Secondary": "n/a"
			},
			"Temperature": 28
		},
		"4": {
			"Biome": "Frozen",
			"Name": "Bqebia",
			"Objectites": {
				"Primary": "n/a",
				"Secondary": "n/a"
			},
			"Temperature": -64
		},
		"5": {
			"Biome": "Stony",
			"Name": "Meh",
			"Objectites": {
				"Primary": "n/a",
				"Secondary": "n/a"
			},
			"Temperature": 15
		},
		"6": {
			"Biome": "Vulcanic",
			"Name": "Hebujojuibi",
			"Objectites": {
				"Primary": "n/a",
				"Secondary": "n/a"
			},
			"Temperature": 87
		}
	},
	"Yotta Belt": {
		"1": {
			"Biome": "Frozen",
			"Name": "Quuhe",
			"Objectites": {
				"Primary": "n/a",
				"Secondary": "n/a"
			},
			"Temperature": -49
		},
		"2": {
			"Biome": "Frozen",
			"Name": "Gajqoq",
			"Objectites": {
				"Primary": "n/a",
				"Secondary": "n/a"
			},
			"Temperature": -58
		},
		"3": {
			"Biome": "Vulcanic",
			"Name": "Zas",
			"Objectites": {
				"Primary": "n/a",
				"Secondary": "n/a"
			},
			"Temperature": 76
		}
	}
}