{
	"Delta Belt": {
		"1": {
			"Biome": "Vulcanic",
			"Name": "Eywi-Qila",
			"Objectites": {
				"Primary": "n/a",
				"Secondary": "n/a"
			},
			"Temperature": 76
		},
		"2": {
			"Biome": "Swamp",
			"Name": "Ceenomu",
			"Objectites": {
				"Primary": "n/a",
				"Secondary": "n/a"
			},
			"Temperature": -2
		},
		"3": {
			"Biome": "Vulcanic",
			"Name": "Vusnid",
			"Objectites": {
				"Primary": "n/a",
				"Secondary": "n/a"
			},
			"Temperature": 90
		},
		"4": {
			"Biome": "Vulcanic",
			"Name": "Pofyus",
			"Objectites": {
				"Primary": "n/a",
				"Secondary": "n/a"
			},
			"Temperature": 83
		},
		"5": {
			"Biome": "Stony",
			"Name": "Awcuu",
			"Objectites": {
				"Primary": "n/a",
				"Secondary": "n/a"
			},
			"Temperature": 17
		}
	},
	"Gamma Field": {
		"1": {
			"Biome": "Stony",
			"Name": "Zahixixiuzu",
			"Objectites": {
				"Primary": "n/a",
				"Secondary": "n/a"
			},
			"Temperature": 21
		},
		"2": {
			"Biome": "Vulcanic",
			"Name": "Uzca-Keku",
			"Objectites": {
				"Primary": "n/a",
				"Secondary": "n/a"
			},
			"Temperature": 88
		},
		"3": {
			"Biome": "Swamp",
			"Name": "Puibu",
			"Objectites": {
				"Primary": "n/a",
				"Secondary": "n/a"
			},
			"Temperature": 5
		},
		"4": {
			"Biome": "Frozen",
			"Name": "Ivku-Nide",
			"Objectites": {
				"Primary": "n/a",
				"Secondary": "n/a"
			},
			"Temperature": -51
		},
		"5": {
			"Biome": "Stony",
			"Name": "Tvuzie",
			"Objectites": {
				"Primary": "n/a",
				"Secondary": "n/a"
			},
			"Temperature": 24
		},
		"6": {
			"Biome": "Vulcanic",
			"Name": "Vahsit",
			"Objectites": {
				"Primary": "n/a",
				"Secondary": "n/a"
			},
			"Temperature": 85
		},
		"7": {
			"Biome": "Vulcanic",
			"Name": "Caxahiheipa",
			"Objectites": {
				"Primary": "n/a",
				"Secondary": "n/a"
			},
			"Temperature": 88
		}
	},
	"Koppa Belt": {
		"1": {
			"Biome": "Frozen",
			"Name": "Wox",
			"Objectites": {
				"Primary": "n/a",
				"Secondary": "n/a"
			},
			"Temperature": -63
		},
		"2": {
			"Biome": "Swamp",
			"Name": "Nopededeixo",
			"Objectites": {
				"Primary": "n/a",
				"Secondary": "n/a"
			},
			"Temperature": 10
		},
		"3": {
			"Biome": "Swamp",
			"Name": "Deyvuy",
			"Objectites": {
				"Primary": "n/a",
				"Secondary": "n/a"
			},
			"Temperature": 0
		},
		"4": {
			"Biome": "Stony",
			"Name": "Buoja",
			"Objectites": {
				"Primary": "n/a",
				"Secondary": "n/a"
			},
			"Temperature": 28
		},
		"5": {
			"Biome": "Stony",
			"Name": "Bis",
			"Objectites": {
				"Primary": "n/a",
				"Secondary": "n/a"
			},
			"Temperature": 20
		},
		"6": {
			"Biome": "Stony",
			"Name": "Yeepuuxgu",
			"Objectites": {
				"Primary": "n/a",
				"Secondary": "n/a"
			},
			"Temperature": 24
		}
	},
	"Omega Field": {
		"1": {
			"Biome": "Swamp",
			"Name": "Giuga",
			"Objectites": {
				"Primary": "n/a",
				"Secondary": "n/a"
			},
			"Temperature": 7
		},
		"2": {
			"Biome": "Stony",
			"Name": "Oyga-Qahi",
			"Objectites": {
				"Primary": "n/a",
				"Secondary": "n/a"
			},
			"Temperature": 27
		},
		"3": {
			"Biome": "Swamp",
			"Name": "Kiomuijwo",
			"Objectites": {
				"Primary": "n/a",
				"Secondary": "n/a"
			},
			"Temperature": -1
		},
		"4": {
			"Biome": "Vulcanic",
			"Name": "Keg",
			"Objectites": {
				"Primary": "n/a",
				"Secondary": "n/a"
			},
			"Temperature": 76
		},
		"5": {
			"Biome": "Vulcanic",
			"Name": "Leewube",
			"Objectites": {
				"Primary": "n/a",
				"Secondary": "n/a"
			},
			"Temperature": 79
		},
		"6": {
			"Biome": "Stony",
			"Name": "Jit",
			"Objectites": {
				"Primary": "n/a",
				"Secondary": "n/a"
			},
			"Temperature": 21
		},
		"7": {
			"Biome": "Swamp",
			"Name": "Woc",
			"Objectites": {
				"Primary": "n/a",
				"Secondary": "n/a"
			},
			"Temperature": -5
		},
		"8": {
			"Biome": "Vulcanic",
			"Name": "Cij",
			"Objectites": {
				"Primary": "n/a",
				"Secondary": "n/a"
			},
			"Temperature": 79
		}
	}
}